midi_notes/__init__.py
midi_notes/scripts/note_info.py
midi_notes-1.1.1.dist-info/entry_points.txt
midi_notes-1.1.1.dist-info/LICENSE
midi_notes-1.1.1.dist-info/WHEEL
midi_notes-1.1.1.dist-info/METADATA
midi_notes-1.1.1.dist-info/RECORD
