Metadata-Version: 2.1
Name: midi_notes
Version: 1.1.1
Summary: Various tables (dicts) and functions for converting between note names, midi
Author-email: Leon Dionne <ldionne@dridesign.sh.cn>
Classifier: License :: OSI Approved :: GNU General Public License v3 or later (GPLv3+)
Classifier: Programming Language :: Python
Classifier: Programming Language :: Python :: 3.10
Classifier: Topic :: Multimedia :: Sound/Audio :: MIDI
Project-URL: Home, https://github.com/Zen-Master-SoSo/midi_notes
